{"nodes": [{"id": "c_users_admin_desktop_projects_swap_docs_setup_guide_md", "label": "setup-guide.md", "file_type": "document", "source_file": "docs/setup-guide.md", "source_location": "L1"}, {"id": "docs_setup_guide_justswap_setup_guide", "label": "JustSwap \u2014 Setup Guide", "file_type": "document", "source_file": "docs/setup-guide.md", "source_location": "L1"}, {"id": "docs_setup_guide_prerequisites", "label": "Prerequisites", "file_type": "document", "source_file": "docs/setup-guide.md", "source_location": "L3"}, {"id": "docs_setup_guide_1_install_dependencies", "label": "1. Install dependencies", "file_type": "document", "source_file": "docs/setup-guide.md", "source_location": "L10"}, {"id": "docs_setup_guide_2_run_the_web_app_works_even_without_supabase", "label": "2. Run the web app (works even without Supabase)", "file_type": "document", "source_file": "docs/setup-guide.md", "source_location": "L20"}, {"id": "docs_setup_guide_3_configure_supabase_env_files", "label": "3. Configure Supabase + env files", "file_type": "document", "source_file": "docs/setup-guide.md", "source_location": "L31"}, {"id": "docs_setup_guide_4_run_migrations_seed", "label": "4. Run migrations + seed", "file_type": "document", "source_file": "docs/setup-guide.md", "source_location": "L49"}, {"id": "docs_setup_guide_demo_data_flag", "label": "Demo-data flag", "file_type": "document", "source_file": "docs/setup-guide.md", "source_location": "L88"}, {"id": "docs_setup_guide_5_storage", "label": "5. Storage", "file_type": "document", "source_file": "docs/setup-guide.md", "source_location": "L101"}, {"id": "docs_setup_guide_6_run_the_backend_api_nestjs", "label": "6. Run the backend API (NestJS)", "file_type": "document", "source_file": "docs/setup-guide.md", "source_location": "L106"}, {"id": "docs_setup_guide_7_run_the_mobile_skeleton", "label": "7. Run the mobile skeleton", "file_type": "document", "source_file": "docs/setup-guide.md", "source_location": "L123"}, {"id": "docs_setup_guide_useful_root_scripts", "label": "Useful root scripts", "file_type": "document", "source_file": "docs/setup-guide.md", "source_location": "L132"}, {"id": "docs_setup_guide_troubleshooting", "label": "Troubleshooting", "file_type": "document", "source_file": "docs/setup-guide.md", "source_location": "L143"}], "edges": [{"source": "c_users_admin_desktop_projects_swap_docs_setup_guide_md", "target": "docs_setup_guide_justswap_setup_guide", "relation": "contains", "confidence": "EXTRACTED", "source_file": "docs/setup-guide.md", "source_location": "L1", "weight": 1.0}, {"source": "docs_setup_guide_justswap_setup_guide", "target": "docs_setup_guide_prerequisites", "relation": "contains", "confidence": "EXTRACTED", "source_file": "docs/setup-guide.md", "source_location": "L3", "weight": 1.0}, {"source": "docs_setup_guide_justswap_setup_guide", "target": "docs_setup_guide_1_install_dependencies", "relation": "contains", "confidence": "EXTRACTED", "source_file": "docs/setup-guide.md", "source_location": "L10", "weight": 1.0}, {"source": "docs_setup_guide_justswap_setup_guide", "target": "docs_setup_guide_2_run_the_web_app_works_even_without_supabase", "relation": "contains", "confidence": "EXTRACTED", "source_file": "docs/setup-guide.md", "source_location": "L20", "weight": 1.0}, {"source": "docs_setup_guide_justswap_setup_guide", "target": "docs_setup_guide_3_configure_supabase_env_files", "relation": "contains", "confidence": "EXTRACTED", "source_file": "docs/setup-guide.md", "source_location": "L31", "weight": 1.0}, {"source": "docs_setup_guide_justswap_setup_guide", "target": "docs_setup_guide_4_run_migrations_seed", "relation": "contains", "confidence": "EXTRACTED", "source_file": "docs/setup-guide.md", "source_location": "L49", "weight": 1.0}, {"source": "docs_setup_guide_4_run_migrations_seed", "target": "docs_setup_guide_demo_data_flag", "relation": "contains", "confidence": "EXTRACTED", "source_file": "docs/setup-guide.md", "source_location": "L88", "weight": 1.0}, {"source": "docs_setup_guide_justswap_setup_guide", "target": "docs_setup_guide_5_storage", "relation": "contains", "confidence": "EXTRACTED", "source_file": "docs/setup-guide.md", "source_location": "L101", "weight": 1.0}, {"source": "docs_setup_guide_justswap_setup_guide", "target": "docs_setup_guide_6_run_the_backend_api_nestjs", "relation": "contains", "confidence": "EXTRACTED", "source_file": "docs/setup-guide.md", "source_location": "L106", "weight": 1.0}, {"source": "docs_setup_guide_justswap_setup_guide", "target": "docs_setup_guide_7_run_the_mobile_skeleton", "relation": "contains", "confidence": "EXTRACTED", "source_file": "docs/setup-guide.md", "source_location": "L123", "weight": 1.0}, {"source": "docs_setup_guide_justswap_setup_guide", "target": "docs_setup_guide_useful_root_scripts", "relation": "contains", "confidence": "EXTRACTED", "source_file": "docs/setup-guide.md", "source_location": "L132", "weight": 1.0}, {"source": "docs_setup_guide_justswap_setup_guide", "target": "docs_setup_guide_troubleshooting", "relation": "contains", "confidence": "EXTRACTED", "source_file": "docs/setup-guide.md", "source_location": "L143", "weight": 1.0}], "input_tokens": 0, "output_tokens": 0}